coinhome/__init__.py
coinhome/module1.py
coinhome/module2.py
coinhone-0.1.dist-info/METADATA
coinhone-0.1.dist-info/WHEEL
coinhone-0.1.dist-info/top_level.txt
coinhone-0.1.dist-info/RECORD
