Metadata-Version: 2.1
Name: coinhone
Version: 0.1
Summary: coinhone of lucky
Home-page: UNKNOWN
Author: wade
Author-email: weishadev@gmail.com
License: UNKNOWN
Platform: UNKNOWN
